{
  "id": "zhiku_battle_expanded",
  "title": "战斗机制·扩展资料",
  "description": "补足战斗正文里常用的机制词、局面词和压制词。",
  "entries": [
    {
      "标题": "弱点击破",
      "分类": "system",
      "摘要": "弱点击破适合作为战斗叙事中的关键转折，表示敌方防线被打穿，局势开始逆转。",
      "原文": "## 基础信息\n\n名称：弱点击破\n类别：战斗机制 / 局势转折\n相关体系：战斗、命途、正文描写\n\n## 说明\n\n弱点击破适合表现“这一击打到了关键处”的感觉。它不只是伤害，更是让敌人失去稳定节奏的转折点。\n\n## 使用要点\n\n- 适合正文战斗转折、技能命中和节奏反转。\n- 写法上要强调破口被打开、敌方阵线松动。\n- 可与命途、技能、状态异常联动。",
      "来源": "项目整理 / 战斗机制扩展",
      "关键词": ["弱点击破", "击破", "转折", "战斗", "命途", "破口"],
      "重要度": 5,
      "可用于联动": true
    },
    {
      "标题": "追加攻击",
      "分类": "system",
      "摘要": "追加攻击适合表现被触发的追击、连锁和补刀动作，让战斗更有连续性。",
      "原文": "## 基础信息\n\n名称：追加攻击\n类别：战斗机制 / 连锁打击\n相关体系：战斗、技能、正文描写\n\n## 说明\n\n追加攻击适合写成“在主动作之后又补上一段动作”的机制。它让战斗更像连续事件，而不是一锤定音。\n\n## 使用要点\n\n- 适合追击、补刀、连锁和协同攻击。\n- 正文里可以表现为突然补上的一击或协同反应。\n- 与战技、状态效果和角色特性联动。",
      "来源": "项目整理 / 战斗机制扩展",
      "关键词": ["追加攻击", "追击", "连锁", "补刀", "战斗", "技能"],
      "重要度": 4,
      "可用于联动": true
    },
    {
      "标题": "反击",
      "分类": "system",
      "摘要": "反击适合表现受击后立即回敬的动作逻辑，强调战斗的攻防对抗。",
      "原文": "## 基础信息\n\n名称：反击\n类别：战斗机制 / 受击回敬\n相关体系：战斗、防御、正文描写\n\n## 说明\n\n反击是一种很适合正文表现的战斗节奏：先受压，再回手。它能把防守转成下一轮进攻。\n\n## 使用要点\n\n- 适合防守反击、受击回手和局部逆转。\n- 可以写得干脆、利落，不需要复杂解释。\n- 与护盾、减伤、状态异常联动效果很好。",
      "来源": "项目整理 / 战斗机制扩展",
      "关键词": ["反击", "防守反击", "受击", "战斗", "回敬", "防御"],
      "重要度": 4,
      "可用于联动": true
    },
    {
      "标题": "行动条压制",
      "分类": "system",
      "摘要": "行动条压制适合描述抢先、拖延和节奏控制，让战斗有更明确的先后顺序感。",
      "原文": "## 基础信息\n\n名称：行动条压制\n类别：战斗机制 / 节奏控制\n相关体系：战斗、控制、正文描写\n\n## 说明\n\n行动条压制适合表现一方通过控制节奏，把对手拖慢或抢先出手的情况。它在文本里很适合体现“局势被压着走”的感觉。\n\n## 使用要点\n\n- 适合控制、拖延、抢先和节奏争夺。\n- 可与减速、眩晕和打断联动。\n- 重点是让战斗的先后顺序更有压迫感。",
      "来源": "项目整理 / 战斗机制扩展",
      "关键词": ["行动条压制", "节奏", "控制", "抢先", "拖延", "战斗"],
      "重要度": 4,
      "可用于联动": true
    },
    {
      "标题": "护盾与减伤",
      "分类": "system",
      "摘要": "护盾与减伤适合表现防线、缓冲和承压能力，让角色在高压下有更清楚的防御层次。",
      "原文": "## 基础信息\n\n名称：护盾与减伤\n类别：战斗机制 / 防护层\n相关体系：战斗、防御、状态\n\n## 说明\n\n护盾与减伤适合写成承受冲击的缓冲层。它让角色不是硬挨，而是先经过一层保护再承受伤害。\n\n## 使用要点\n\n- 适合防守、保护队友和承压场景。\n- 可写成防线、护罩、装甲或临时屏障。\n- 与战斗履历、状态异常和重大战斗联动。",
      "来源": "项目整理 / 战斗机制扩展",
      "关键词": ["护盾", "减伤", "防护", "战斗", "承压", "防线"],
      "重要度": 4,
      "可用于联动": true
    },
    {
      "标题": "状态异常",
      "分类": "system",
      "摘要": "状态异常适合表现中毒、冻结、灼烧、虚弱等战斗附加效果，让战斗结果更有文本重量。",
      "原文": "## 基础信息\n\n名称：状态异常\n类别：战斗机制 / 附加效果\n相关体系：战斗、正文、叙事后果\n\n## 说明\n\n状态异常适合承担“战斗不只是掉血”的那一层表现。角色会因为不同状态而出现迟缓、疼痛、失衡或持续受压。\n\n## 使用要点\n\n- 适合冻伤、灼烧、中毒、虚弱、眩晕等效果。\n- 正文里优先写身体反应，不必直接堆数值。\n- 与 NPC 同行记忆、世界事件、新闻苗头和命途效果联动。",
      "来源": "项目整理 / 战斗机制扩展",
      "关键词": ["状态异常", "灼烧", "冻结", "中毒", "虚弱", "眩晕"],
      "重要度": 5,
      "可用于联动": true
    },
    {
      "标题": "首领战",
      "分类": "system",
      "摘要": "首领战适合表现高压、阶段变化和终局感，强调敌方存在感与战斗戏剧性。",
      "原文": "## 基础信息\n\n名称：首领战\n类别：战斗场景 / 高压对抗\n相关体系：剧情、战斗、重大事件\n\n## 说明\n\n首领战适合承担大场面、阶段转换和剧情重压。它不是普通交火，而是需要明确写出节奏、压迫和转折的战斗。\n\n## 使用要点\n\n- 适合章节尾战、灾厄事件和剧情关键节点。\n- 可强调阶段切换、爆发、压制和反转。\n- 与新闻、剧情后果、NPC 记忆和世界事件联动。",
      "来源": "项目整理 / 战斗机制扩展",
      "关键词": ["首领战", "boss", "高压", "阶段", "转折", "战斗"],
      "重要度": 5,
      "可用于联动": true
    }
  ]
}
